beepmusic/__init__.py
beepmusic/__main__.py
beepmusic/beepmusic.py
beepmusic/musicLaw.py
beepmusic/parser.py
beepmusic/builtin_musics/joy.bmc
beepmusic/builtin_musics/蜜雪冰城.bmc
beepmusic-0.0.3.dist-info/LICENSE
beepmusic-0.0.3.dist-info/METADATA
beepmusic-0.0.3.dist-info/WHEEL
beepmusic-0.0.3.dist-info/top_level.txt
beepmusic-0.0.3.dist-info/RECORD
