Metadata-Version: 2.1
Name: beepmusic
Version: 0.0.3
Summary: Play music using computer beep prompt tone.
Home-page: https://github.com/ChrisChemHater/BeepMusic
Author: Chris Pan
Author-email: pgx@pku.edu.cn
License: UNKNOWN
Project-URL: Bug Tracker, https://github.com/ChrisChemHater/BeepMusic/issues
Platform: UNKNOWN
Classifier: Programming Language :: Python :: 3
Classifier: License :: OSI Approved :: MIT License
Classifier: Operating System :: OS Independent
Requires-Python: >=3.6
License-File: LICENSE
